.DS_Store
foodparser/__init__.py
foodparser/foodparser.py
foodparser/data/combined_gram_set.csv
foodparser/data/test.txt
foodparser-0.1.10.dist-info/LICENSE
foodparser-0.1.10.dist-info/METADATA
foodparser-0.1.10.dist-info/WHEEL
foodparser-0.1.10.dist-info/top_level.txt
foodparser-0.1.10.dist-info/RECORD
