Metadata-Version: 2.1
Name: foodparser
Version: 0.1.10
Summary: A package to parse food logging texts.
Home-page: https://github.com/JoeyHou/food_parser
Author: Joey Hou
Author-email: z9hou@ucsd.edu
License: UNKNOWN
Platform: UNKNOWN
Classifier: Programming Language :: Python :: 3.7
Classifier: License :: OSI Approved :: GNU General Public License v3 (GPLv3)
